scrublet/__init__.py
scrublet/helper_functions.py
scrublet/scrublet.py
scrublet-0.2.2.dist-info/LICENSE
scrublet-0.2.2.dist-info/METADATA
scrublet-0.2.2.dist-info/WHEEL
scrublet-0.2.2.dist-info/top_level.txt
scrublet-0.2.2.dist-info/RECORD
