Metadata-Version: 2.1
Name: scrublet
Version: 0.2.2
Summary: Doublet prediction in single-cell RNA-sequencing data
Home-page: https://github.com/swolock/scrublet
Author: Samuel L. Wolock
Author-email: swolock@gmail.com
License: UNKNOWN
Platform: UNKNOWN
Requires-Dist: cython
Requires-Dist: numpy
Requires-Dist: scipy
Requires-Dist: scikit-learn
Requires-Dist: scikit-image
Requires-Dist: matplotlib
Requires-Dist: annoy
Requires-Dist: numba
Requires-Dist: pandas
Requires-Dist: umap-learn
